README.md
setup.py
cripto_aps2/__init__.py
cripto_aps2/funcoes.py
cripto_aps2.egg-info/PKG-INFO
cripto_aps2.egg-info/SOURCES.txt
cripto_aps2.egg-info/dependency_links.txt
cripto_aps2.egg-info/requires.txt
cripto_aps2.egg-info/top_level.txt