Metadata-Version: 2.1
Name: cripto_aps2
Version: 0.1.1.1
Summary: Biblioteca para criptografia e descriptografia de mensagens
Home-page: https://github.com/shuds13/pyexample
Author: Giovanny Russo
Author-email: giovannyjrusso@gmail.com
License: BSD 2-clause
Classifier: Development Status :: 1 - Planning
Classifier: Intended Audience :: Science/Research
Classifier: License :: OSI Approved :: BSD License
Classifier: Operating System :: POSIX :: Linux
Classifier: Programming Language :: Python :: 2
Classifier: Programming Language :: Python :: 2.7
Classifier: Programming Language :: Python :: 3
Classifier: Programming Language :: Python :: 3.4
Classifier: Programming Language :: Python :: 3.5
Requires-Dist: numpy>=1.19.5
Requires-Dist: flask>=2.0.1
